Jan27/comb.v
module comb(Out,X,Y,Z);
	//Declaration
	input X,Y,Z;
	output Out;
	wire nand_w1,nand_w2,or_w,not_w;
	//Instantiation
	nand n1(nand_w1,X,Y);
	nand n2(nand_w2,Y,X);
	or o(or_w,nand_w1,nand_w2);
	not n(not_w,Z);
	and a(Out,not_w,or_w);
endmodule

Jan27/comb_test.v
`timescale 1ns/1ns
module comb_test();
	reg X,Y,Z;
	wire Out;
	comb c1 (Out,X,Y,Z);
	initial begin
		$dumpfile("wave.vcd");
		$dumpvars(0,comb_test);
		$monitor("%d %d %d -> %d",X,Y,Z,Out);
		#0 X = 0; Y = 0; Z = 0;
		#2 X = 0; Y = 0; Z = 0;
		#2 X = 0; Y = 0; Z = 1;
		#2 X = 0; Y = 1; Z = 0;
		#2 X = 0; Y = 1; Z = 1;
		#2 X = 1; Y = 0; Z = 0;
		#2 X = 1; Y = 0; Z = 1;
		#2 X = 1; Y = 1; Z = 0;
		#2 X = 1; Y = 1; Z = 1;
		#2 X = 1; Y = 0; Z = 0;
		#2 X = 0; Y = 0; Z = 1;
		#5 $finish;
	end
endmodule

Jan27/wave.vcd
$date
	Thu Jan 27 03:23:31 2022
$end
$version
	Icarus Verilog
$end
$timescale
	1ns
$end
$scope module comb_test $end
$var wire 1 ! Out $end
$var reg 1 " X $end
$var reg 1 # Y $end
$var reg 1 $ Z $end
$scope module c1 $end
$var wire 1 ! Out $end
$var wire 1 " X $end
$var wire 1 # Y $end
$var wire 1 $ Z $end
$var wire 1 % nand_w1 $end
$var wire 1 & nand_w2 $end
$var wire 1 ' not_w $end
$var wire 1 ( or_w $end
$upscope $end
$upscope $end
$enddefinitions $end
#0
$dumpvars
1(
1'
1&
1%
0$
0#
0"
1!
$end
#4
0!
0'
1$
#6
1!
1'
0$
1#
#8
0!
0'
1$
#10
1!
1'
0$
0#
1"
#12
0!
0'
1$
#14
0(
1'
0%
0&
0$
1#
#16
0'
1$
#18
1!
1(
1'
1%
1&
0$
0#
#20
0!
0'
1$
0"
