Assignment_1A/ADDER.v/Half_Adder.v
module Half_Adder(input X,input Y,output S,output C);
    assign S = X ^ Y; //Sum bit of HA
    assign C = X & Y;//Carry bit of HA
endmodule

Assignment_1A/ADDER.v/Full_Adder.v
`include "Half_Adder.v"
module Full_Adder(input X,input Y,input Z,output S,output C);
    wire S1,S2,C1,C2;
    Half_Adder HA1(.X(X),.Y(Y),.S(S1),.C(C1));
    Half_Adder HA2(.X(S1),.Y(Z),.S(S2),.C(C2));
    assign C = C1 | C2;
    assign S = S2;
endmodule

Assignment_1/ADDER.v/Full_Adder_test.v
module Full_Adder_test();
    reg X,Y,Z;
    wire C,S;
    Full_Adder Comb(.X(X),.Y(Y),.Z(Z),.S(S),.C(C));
    initial begin 
        $dumpfile("Full_Adder.vcd");
        $dumpvars(0,Comb);
        $monitor("%d + %d + %d-> %d %d",X,Y,Z,C,S);
        X=0; Y=0; Z=0; #5;
        X=0; Y=0; Z=1; #5;
        X=0; Y=1; Z=0; #5;
        X=0; Y=1; Z=1; #5;
        X=1; Y=0; Z=0; #5;
        X=1; Y=0; Z=1; #5;
        X=1; Y=1; Z=0; #5;
        X=1; Y=1; Z=1; #5;
        $finish;
    end 
endmodule

Assignment_1A/ADDER.v/Full_Adder.vcd
$date
	Wed Mar 30 02:27:14 2022
$end
$version
	Icarus Verilog
$end
$timescale
	1s
$end
$scope module Full_Adder_test $end
$scope module Comb $end
$var wire 1 ! C $end
$var wire 1 " S $end
$var wire 1 # X $end
$var wire 1 $ Y $end
$var wire 1 % Z $end
$var wire 1 & S2 $end
$var wire 1 ' S1 $end
$var wire 1 ( C2 $end
$var wire 1 ) C1 $end
$scope module HA1 $end
$var wire 1 ) C $end
$var wire 1 ' S $end
$var wire 1 # X $end
$var wire 1 $ Y $end
$upscope $end
$scope module HA2 $end
$var wire 1 ( C $end
$var wire 1 & S $end
$var wire 1 ' X $end
$var wire 1 % Y $end
$upscope $end
$upscope $end
$upscope $end
$enddefinitions $end
#0
$dumpvars
0)
0(
0'
0&
0%
0$
0#
0"
0!
$end
#5
1"
1&
1%
#10
1'
0%
1$
#15
1!
0"
0&
1(
1%
#20
0!
1"
1&
0(
0%
0$
1#
#25
1!
0"
0&
1(
1%
#30
0(
0'
1)
0%
1$
#35
1"
1&
1%
