Assignment_1/Substractor/Half_Substractor.v
module Half_Substractor(input X,input Y,output D,output B);
    assign D = X ^ Y;
    assign B = (~X) & Y;
endmodule

Assignment_1A/Substractor/Full_Substractor.v
`include "Half_Substractor.v"
module Full_Substractor(input X,input Y,input Z,output D,output B);
    wire D1,D2,B1,B2;
    Half_Substractor HS1(.X(X),.Y(Y),.B(B1),.D(D1));
    Half_Substractor HS2(.X(D1),.Y(Z),.B(B2),.D(D2));
    assign B = B1 | B2;
    assign D = D2;
endmodule

Assignment_1/Substractor/Full_Substractor_test.v
module Full_Substractor_test();
    reg X,Y,Z;
    wire D,B;
    Full_Substractor Comb(.X(X),.Y(Y),.Z(Z),.D(D),.B(B));
    initial begin 
        $dumpfile("Full_Substractor.vcd");
        $dumpvars(0,Comb);
        $monitor("%d - %d - %d-> %d %d",X,Y,Z,B,D);
        X=0; Y=0; Z=0; #5;
        X=0; Y=0; Z=1; #5;
        X=0; Y=1; Z=0; #5;
        X=0; Y=1; Z=1; #5;
        X=1; Y=0; Z=0; #5;
        X=1; Y=0; Z=1; #5;
        X=1; Y=1; Z=0; #5;
        X=1; Y=1; Z=1; #5;
        $finish;
    end 
endmodule

Assignment_1A/Substractor/Full_Substractor.vcd
$date
	Wed Mar 30 02:42:19 2022
$end
$version
	Icarus Verilog
$end
$timescale
	1s
$end
$scope module Full_Substractor_test $end
$scope module Comb $end
$var wire 1 ! B $end
$var wire 1 " D $end
$var wire 1 # X $end
$var wire 1 $ Y $end
$var wire 1 % Z $end
$var wire 1 & D2 $end
$var wire 1 ' D1 $end
$var wire 1 ( B2 $end
$var wire 1 ) B1 $end
$scope module HS1 $end
$var wire 1 ) B $end
$var wire 1 ' D $end
$var wire 1 # X $end
$var wire 1 $ Y $end
$upscope $end
$scope module HS2 $end
$var wire 1 ( B $end
$var wire 1 & D $end
$var wire 1 ' X $end
$var wire 1 % Y $end
$upscope $end
$upscope $end
$upscope $end
$enddefinitions $end
#0
$dumpvars
0)
0(
0'
0&
0%
0$
0#
0"
0!
$end
#5
1!
1"
1&
1(
1%
#10
0(
1'
1)
0%
1$
#15
0"
0&
1%
#20
0!
1"
1&
0)
0%
0$
1#
#25
0"
0&
1%
#30
0'
0%
1$
#35
1!
1"
1&
1(
1%
